gsheet_mcp_server/__init__.py
gsheet_mcp_server/__main__.py
gsheet_mcp_server/models.py
gsheet_mcp_server/server.py
gsheet_mcp_server/setup.py
gsheet_mcp_server/handler/__init__.py
gsheet_mcp_server/handler/content_manipulation/__init__.py
gsheet_mcp_server/handler/sheets/__init__.py
gsheet_mcp_server/handler/sheets/analyze_sheet_structure_handler.py
gsheet_mcp_server/handler/sheets/create_duplicate_sheet_handler.py
gsheet_mcp_server/handler/sheets/create_sheets_handler.py
gsheet_mcp_server/handler/sheets/delete_sheets_handler.py
gsheet_mcp_server/handler/sheets/update_sheet_titles_handler.py
gsheet_mcp_server/handler/spreadsheet/__init__.py
gsheet_mcp_server/handler/spreadsheet/discover_spreadsheets_handler.py
gsheet_mcp_server/handler/spreadsheet/update_spreadsheet_title_handler.py
gsheet_mcp_server/handler/tables/__init__.py
gsheet_mcp_server/handler/tables/add_table_column_handler.py
gsheet_mcp_server/handler/tables/add_table_records_handler.py
gsheet_mcp_server/handler/tables/create_table_handler.py
gsheet_mcp_server/handler/tables/delete_table_column_handler.py
gsheet_mcp_server/handler/tables/delete_table_handler.py
gsheet_mcp_server/handler/tables/delete_table_records_handler.py
gsheet_mcp_server/handler/tables/get_sheet_cells_by_notation_handler.py
gsheet_mcp_server/handler/tables/get_sheet_cells_by_range_handler.py
gsheet_mcp_server/handler/tables/get_table_data_handler.py
gsheet_mcp_server/handler/tables/get_table_metadata_handler.py
gsheet_mcp_server/handler/tables/update_dropdown_options_handler.py
gsheet_mcp_server/handler/tables/update_table_cells_by_notation_handler.py
gsheet_mcp_server/handler/tables/update_table_cells_by_range_handler.py
gsheet_mcp_server/handler/tables/update_table_column_name_handler.py
gsheet_mcp_server/handler/tables/update_table_column_type_handler.py
gsheet_mcp_server/handler/tables/update_table_sorting_handler.py
gsheet_mcp_server/handler/tables/update_table_title_handler.py
gsheet_mcp_server/helper/__init__.py
iflow_mcp_henilcalagiya_google_sheets_mcp-0.1.6.dist-info/METADATA
iflow_mcp_henilcalagiya_google_sheets_mcp-0.1.6.dist-info/WHEEL
iflow_mcp_henilcalagiya_google_sheets_mcp-0.1.6.dist-info/entry_points.txt
iflow_mcp_henilcalagiya_google_sheets_mcp-0.1.6.dist-info/licenses/LICENSE
iflow_mcp_henilcalagiya_google_sheets_mcp-0.1.6.dist-info/RECORD
